MANIFEST.in
README.md
setup.py
etc/colab/plugins.d/edemocracia.py
src/colab_edemocracia/__init__.py
src/colab_edemocracia/admin.py
src/colab_edemocracia/api.py
src/colab_edemocracia/apps.py
src/colab_edemocracia/captcha.py
src/colab_edemocracia/choices.py
src/colab_edemocracia/data_importer.py
src/colab_edemocracia/diazo.xml
src/colab_edemocracia/middlewares.py
src/colab_edemocracia/models.py
src/colab_edemocracia/package.json
src/colab_edemocracia/processors.py
src/colab_edemocracia/search_indexes.py
src/colab_edemocracia/serializers.py
src/colab_edemocracia/urls.py
src/colab_edemocracia/utils.py
src/colab_edemocracia/views.py
src/colab_edemocracia.egg-info/PKG-INFO
src/colab_edemocracia.egg-info/SOURCES.txt
src/colab_edemocracia.egg-info/dependency_links.txt
src/colab_edemocracia.egg-info/not-zip-safe
src/colab_edemocracia.egg-info/requires.txt
src/colab_edemocracia.egg-info/top_level.txt
src/colab_edemocracia/forms/__init__.py
src/colab_edemocracia/forms/accounts.py
src/colab_edemocracia/management/__init__.py
src/colab_edemocracia/management/commands/__init__.py
src/colab_edemocracia/management/commands/fetch_data.py
src/colab_edemocracia/management/commands/import_edemocracia_users.py
src/colab_edemocracia/management/commands/send_mail_marketing.py
src/colab_edemocracia/migrations/0001_initial.py
src/colab_edemocracia/migrations/0002_remove_userprofile_photo.py
src/colab_edemocracia/migrations/0003_auto_20160921_2156.py
src/colab_edemocracia/migrations/0004_userprofile_country.py
src/colab_edemocracia/migrations/0005_userprofile_birthyear.py
src/colab_edemocracia/migrations/0006_auto_20170908_2045.py
src/colab_edemocracia/migrations/0007_auto_20171006_1902.py
src/colab_edemocracia/migrations/0008_remove_userprofile_birthyear.py
src/colab_edemocracia/migrations/__init__.py
src/colab_edemocracia/static/img/edem-logo-full.png
src/colab_edemocracia/static/img/edem-logo-text-title.d40f8964006f.png
src/colab_edemocracia/static/img/edem-logo-text-title.png
src/colab_edemocracia/static/img/edem-logo-text.png
src/colab_edemocracia/static/img/edem-logo.png
src/colab_edemocracia/static/img/leftleak.svg
src/colab_edemocracia/static/img/logo-audiencias-icon.svg
src/colab_edemocracia/static/img/logo-audiencias-publicas.png
