Metadata-Version: 1.1
Name: colab-edemocracia
Version: 1.2.0
Summary: Colab Edemocracia Colab plugin
Home-page: https://github.com/labhackercd/colab-edemocracia-plugin
Author: labhackercd
Author-email: labhackercd@gmail.com
License: gpl3
Platform: UNKNOWN
Classifier: Framework :: Django
Classifier: Intended Audience :: Developers
Classifier: Intended Audience :: System Administrators
Classifier: Operating System :: OS Independent
Classifier: Topic :: Software Development
